document_detection/__init__.py
document_detection/detection.py
document_detection/node.py
document_detection/scope_table
document_detection/state_word.txt
document_detection/test.py
document_detection/utils.py
documennt_detection-1.0.3.dist-info/METADATA
documennt_detection-1.0.3.dist-info/WHEEL
documennt_detection-1.0.3.dist-info/top_level.txt
documennt_detection-1.0.3.dist-info/RECORD
