Metadata-Version: 2.1
Name: documennt-detection
Version: 1.0.3
Summary: version
Home-page: https://pypi.org/project/documennt_detection
Author: huyi
Author-email: huyi@datagrand.com
Requires-Python: >=3.6.0
Requires-Dist: Levenshtein (==0.20.9)
